deeperhistreg/__init__.py
deeperhistreg/run.py
deeperhistreg/dhr_creators/__init__.py
deeperhistreg/dhr_datasets/__init__.py
deeperhistreg/dhr_deformation/__init__.py
deeperhistreg/dhr_deformation/apply_deformation.py
deeperhistreg/dhr_evaluation/__init__.py
deeperhistreg/dhr_evaluation/evaluation.py
deeperhistreg/dhr_experiments/__init__.py
deeperhistreg/dhr_input_output/__init__.py
deeperhistreg/dhr_input_output/input_output.py
deeperhistreg/dhr_input_output/dhr_loaders/__init__.py
deeperhistreg/dhr_input_output/dhr_loaders/cucim_loader.py
deeperhistreg/dhr_input_output/dhr_loaders/displacement_loader.py
deeperhistreg/dhr_input_output/dhr_loaders/loader.py
deeperhistreg/dhr_input_output/dhr_loaders/openslide_loader.py
deeperhistreg/dhr_input_output/dhr_loaders/pair_full_loader.py
deeperhistreg/dhr_input_output/dhr_loaders/pil_loader.py
deeperhistreg/dhr_input_output/dhr_loaders/simple_loader.py
deeperhistreg/dhr_input_output/dhr_loaders/sitk_loader.py
deeperhistreg/dhr_input_output/dhr_loaders/tiff_loader.py
deeperhistreg/dhr_input_output/dhr_loaders/vips_loader.py
deeperhistreg/dhr_input_output/dhr_parsers/__init__.py
deeperhistreg/dhr_input_output/dhr_savers/__init__.py
deeperhistreg/dhr_input_output/dhr_savers/displacement_saver.py
deeperhistreg/dhr_input_output/dhr_savers/pair_full_saver.py
deeperhistreg/dhr_input_output/dhr_savers/pil_saver.py
deeperhistreg/dhr_input_output/dhr_savers/results_saver.py
deeperhistreg/dhr_input_output/dhr_savers/saver.py
deeperhistreg/dhr_input_output/dhr_savers/sitk_saver.py
deeperhistreg/dhr_input_output/dhr_savers/tiff_saver.py
deeperhistreg/dhr_input_output/dhr_savers/vips_saver.py
deeperhistreg/dhr_input_output/dhr_savers/warping_params_saver.py
deeperhistreg/dhr_models/superglue_indoor.pth
deeperhistreg/dhr_models/superglue_outdoor.pth
deeperhistreg/dhr_models/superpoint_v1.pth
deeperhistreg/dhr_networks/__init__.py
deeperhistreg/dhr_networks/superglue.py
deeperhistreg/dhr_networks/superpoint.py
deeperhistreg-1.0.1.dist-info/METADATA
deeperhistreg-1.0.1.dist-info/WHEEL
deeperhistreg-1.0.1.dist-info/licenses/LICENSE
deeperhistreg-1.0.1.dist-info/RECORD
