Metadata-Version: 2.1
Name: deeperhistreg
Version: 1.0.1
Summary: DeeperHistReg Framework - To Register WSI Images
Project-URL: Homepage, https://github.com/MWod/DeeperHistReg
Project-URL: Bug Tracker, https://github.com/MWod/DeeperHistReg/issues
Author-email: Marek Wodzinski <wodzinski@agh.edu.pl>
License-File: LICENSE
Classifier: License :: OSI Approved :: GNU General Public License v3 (GPLv3)
Classifier: Operating System :: OS Independent
Classifier: Programming Language :: Python :: 3
Classifier: Topic :: Scientific/Engineering :: Artificial Intelligence
Classifier: Topic :: Scientific/Engineering :: Image Processing
Requires-Python: >=3.8
